{"$defs":{"ProbenContainerType.MitteilungsgrundContainer":{"type":"object","required":["mitteilungsgrund"],"properties":{"mitteilungsgrund":{"type":"array","items":{"type":"string"},"minItems":1}}},"ProbenContainerType.ProjektNrContainer":{"type":"object","required":["projektNr"],"properties":{"projektNr":{"type":"array","items":{"type":"string"},"minItems":1}}},"ProbenContainerType.TieralterGruppe":{"type":"object","required":["tieralter","tieralterEinheit"],"properties":{"tieralter":{"type":"number"},"tieralterEinheit":{"type":"string"}}},"ProbenContainerType.VerpackungContainer":{"type":"object","required":["verpackung"],"properties":{"verpackung":{"type":"array","items":{"type":"string"},"minItems":1}}},"ProbenContainerType.VerschlussContainer":{"type":"object","required":["verschluss"],"properties":{"verschluss":{"type":"array","items":{"type":"string"},"minItems":1}}},"ProbenContainerType.ExtProbKennungContainer.ExtProbKennungenGruppe":{"type":"object","required":["extProbKennung","extProbKennungArt"],"properties":{"extProbKennung":{"type":"string"},"extProbKennungArt":{"type":"string"}}},"ProbenContainerType.ExtProbKennungContainer":{"type":"object","required":["extProbKennungenGruppe"],"properties":{"extProbKennungenGruppe":{"type":"array","items":{"$ref":"#/$defs/ProbenContainerType.ExtProbKennungContainer.ExtProbKennungenGruppe"},"minItems":1}}},"ProbenContainerType.KennzeichnungZusatzContainer":{"type":"object","required":["kennzeichnungZusatz"],"properties":{"kennzeichnungZusatz":{"type":"array","items":{"type":"string"},"minItems":1}}},"ProbenContainerType.PrimaerprodContainer":{"type":"object","required":["primaerprod"],"properties":{"primaerprod":{"type":"array","items":{"type":"string"},"minItems":1}}},"ProbenContainerType.HerkunftUntersuchGutContainer":{"type":"object","required":["herkunftUntersuchGut"],"properties":{"herkunftUntersuchGut":{"type":"array","items":{"type":"string"},"minItems":1}}},"ProbenContainerType.ProbBeurteilungContainer":{"type":"object","required":["probBeurteilung"],"properties":{"probBeurteilung":{"type":"array","items":{"type":"string"},"minItems":1}}},"ProbenContainerType":{"type":"object","required":["probRefStaNr","probNr","teilprobNr","relationProbRefStaNr","probenahmegrund","probenahmedatum","matrix"],"properties":{"probRefStaNr":{"type":"string"},"extSystemID":{"type":"string"},"probNr":{"type":"string"},"teilprobNr":{"type":"string"},"relationNr":{"type":"string"},"relationProbRefStaNr":{"type":"string"},"probenahmegrund":{"type":"string"},"mitteilungsgrundContainer":{"$ref":"#/$defs/ProbenContainerType.MitteilungsgrundContainer"},"projektNrContainer":{"$ref":"#/$defs/ProbenContainerType.ProjektNrContainer"},"probenahmedatum":{"type":"string","format":"date"},"probenahmegem":{"type":"string"},"probenahmevorschrift":{"type":"string"},"tier":{"type":"string"},"tierrasse":{"type":"string"},"tieralterGruppe":{"$ref":"#/$defs/ProbenContainerType.TieralterGruppe"},"matrix":{"type":"string"},"matrixZusatz":{"type":"string"},"probBestandUntersuch":{"type":"string"},"verpackungContainer":{"$ref":"#/$defs/ProbenContainerType.VerpackungContainer"},"verschlussContainer":{"$ref":"#/$defs/ProbenContainerType.VerschlussContainer"},"extProbKennungContainer":{"$ref":"#/$defs/ProbenContainerType.ExtProbKennungContainer"},"angabeHaltbarkeit":{"type":"string"},"herstellungDatum":{"type":"string"},"bezeichnungGeoSchutz":{"type":"string"},"kennzeichnungZusatzContainer":{"$ref":"#/$defs/ProbenContainerType.KennzeichnungZusatzContainer"},"konzentrationsfaktor":{"type":"number"},"primaerprodContainer":{"$ref":"#/$defs/ProbenContainerType.PrimaerprodContainer"},"haltungsform":{"type":"string"},"betriebsart":{"type":"string"},"ursprungsstaat":{"type":"string"},"sitzHerstellerStaat":{"type":"string"},"sitzHerstellerGem":{"type":"string"},"sitzInverkehrStaat":{"type":"string"},"sitzInverkehrGem":{"type":"string"},"wasserGebiet":{"type":"string"},"herkunftUntersuchGutContainer":{"$ref":"#/$defs/ProbenContainerType.HerkunftUntersuchGutContainer"},"weinbauzone":{"type":"string"},"belastungGebiet":{"type":"string"},"analyseende":{"type":"string","format":"date"},"probBeurteilungContainer":{"$ref":"#/$defs/ProbenContainerType.ProbBeurteilungContainer"}}},"DeliveryContainer.Proben":{"type":"object","properties":{"probenContainer":{"type":"array","items":{"$ref":"#/$defs/ProbenContainerType"},"minItems":0}}},"ErgebnisContainerType.DeklarationGehaltGruppe":{"type":"object","required":["deklarationGehalt","deklarationEinheit"],"properties":{"deklarationGehalt":{"type":"number"},"deklarationEinheit":{"type":"string"}}},"ErgebnisContainerType.MessunsicherheitGruppe":{"type":"object","required":["messunsicherheit","messunsicherEinheit"],"properties":{"messunsicherheit":{"type":"number"},"messunsicherEinheit":{"type":"string"}}},"ErgebnisContainerType":{"type":"object","required":["probRefStaNr","probRefErgNr","parameter","messprinzip"],"properties":{"probRefStaNr":{"type":"string"},"probRefErgNr":{"type":"string"},"parameter":{"type":"string"},"zuordnungFMRecht":{"type":"string"},"deklarationGehaltGruppe":{"$ref":"#/$defs/ErgebnisContainerType.DeklarationGehaltGruppe"},"deklarationBezug":{"type":"string"},"untersuchVerfahren":{"type":"string"},"messprinzip":{"type":"string"},"analyseIdent":{"type":"string"},"analysetyp":{"type":"string"},"akkredStatus":{"type":"string"},"einheit":{"type":"string"},"bezugsparameter":{"type":"string"},"nachweisgrenze":{"type":"number"},"bestimmungsgrenze":{"type":"number"},"ccAlpha":{"type":"number"},"ccBeta":{"type":"number"},"ergNumerisch":{"type":"number"},"wiederfindungsrate":{"type":"number"},"wiederfindKorrigiert":{"type":"string"},"ergNichtNumerisch":{"type":"string"},"messunsicherheitGruppe":{"$ref":"#/$defs/ErgebnisContainerType.MessunsicherheitGruppe"},"ergBewertung":{"type":"string"},"verarbeitungsfaktor":{"type":"string"},"limit":{"type":"number"}}},"DeliveryContainer.Ergebnisse":{"type":"object","properties":{"ergebnisContainer":{"type":"array","items":{"$ref":"#/$defs/ErgebnisContainerType"},"minItems":0}}},"ZusatzContainerType.ZusatzNumerischGruppe":{"type":"object","required":["zusatzNumerisch","zusatzEinheit"],"properties":{"zusatzNumerisch":{"type":"number"},"zusatzEinheit":{"type":"string"}}},"ZusatzContainerType":{"type":"object","required":["zusatzRefTyp","zusatzRefNr"],"properties":{"zusatzRefTyp":{"type":"string"},"zusatzRefNr":{"type":"string"},"zusatzArt":{"type":"string"},"zusatzText":{"type":"string"},"zusatzNumerischGruppe":{"$ref":"#/$defs/ZusatzContainerType.ZusatzNumerischGruppe"}}},"DeliveryContainer.ZusatzDaten":{"type":"object","properties":{"zusatzContainer":{"type":"array","items":{"$ref":"#/$defs/ZusatzContainerType"},"minItems":0}}},"DeliveryContainer":{"type":"object","required":["meldendeStelle"],"properties":{"meldendeStelle":{"type":"string"},"proben":{"$ref":"#/$defs/DeliveryContainer.Proben"},"ergebnisse":{"$ref":"#/$defs/DeliveryContainer.Ergebnisse"},"zusatzDaten":{"$ref":"#/$defs/DeliveryContainer.ZusatzDaten"}}}},"$id":"https://example.com/xsdexample.schema.json","$schema":"http://json-schema.org/draft/2020-12/schema","title":"Example XSD to JSON Schema","type":"object","properties":{"deliveryContainer1":{"$ref":"#/$defs/DeliveryContainer"}}}